scepticoin/__init__.py
scepticoin/__version__.py
scepticoin/cheating.py
scepticoin/coinstate.py
scepticoin/consensus.py
scepticoin/datatypes.py
scepticoin/genesis.py
scepticoin/hash.py
scepticoin/humans.py
scepticoin/merkletree.py
scepticoin/params.py
scepticoin/pow.py
scepticoin/scmversion.py
scepticoin/serialization.py
scepticoin/signing.py
scepticoin/utils.py
scepticoin/wallet.py
scepticoin/networking/messages.py
scepticoin/networking/params.py
scepticoin/networking/peer.py
scepticoin/networking/threading.py
scepticoin/networking/utils.py
scepticoin/scripts/__init__.py
scepticoin/scripts/mine.py
scepticoin/scripts/receive.py
scepticoin/scripts/repl.py
scepticoin/scripts/send.py
scepticoin/scripts/utils.py
scepticoin/scripts/version.py
scepticoin-0.1.8.dist-info/LICENSE
scepticoin-0.1.8.dist-info/METADATA
scepticoin-0.1.8.dist-info/WHEEL
scepticoin-0.1.8.dist-info/entry_points.txt
scepticoin-0.1.8.dist-info/top_level.txt
scepticoin-0.1.8.dist-info/RECORD
