Metadata-Version: 2.1
Name: scepticoin
Version: 0.1.8
Summary: The Coin for Non-Believers
Home-page: https://github.com/scepticoin/scepticoin/
Author: Sashimi Houdini
License: BSD-3-Clause
Platform: UNKNOWN
Classifier: Development Status :: 4 - Beta
Classifier: Environment :: Console
Classifier: Intended Audience :: End Users/Desktop
Classifier: Intended Audience :: Developers
Classifier: License :: OSI Approved :: BSD License
Classifier: Operating System :: MacOS :: MacOS X
Classifier: Operating System :: Microsoft :: Windows
Classifier: Operating System :: POSIX
Classifier: Programming Language :: Python
Requires-Dist: ecdsa (>=0.16.1)
Requires-Dist: immutables (>=0.15)
Requires-Dist: ptpython
Requires-Dist: scrypt (>=0.8.17)
